FlowOpt/__init__.py
FlowOpt/flow_operation.py
FlowOpt/resource/__init__.py
FlowOpt/resource/icons/__init__.py
FlowOpt/resource/icons/chrome_icon.png
FlowOpt/resource/icons/terminal_input_password.png
FlowOpt/resource/icons/vim_insert_end.png
FlowOpt/tools/__init__.py
FlowOpt/tools/file_lock.py
FlowOpt/tools/sqlite_models.py
FlowOpt/tools/time_format.py
resource/__init__.py
resource/icons/__init__.py
test_files/__init__.py
tools/__init__.py
tools/sqlite_models.py
flowoperate-0.1.1.dist-info/LICENSE
flowoperate-0.1.1.dist-info/METADATA
flowoperate-0.1.1.dist-info/WHEEL
flowoperate-0.1.1.dist-info/entry_points.txt
flowoperate-0.1.1.dist-info/top_level.txt
flowoperate-0.1.1.dist-info/RECORD
