Metadata-Version: 2.1
Name: flowoperate
Version: 0.1.1
Summary: control the mouse and keyboard todo repeat jobs
Home-page: https://github.com/ga1008/flowoperate
Author: Guardian
Author-email: zhling2012@live.com
Maintainer: Guardian
Maintainer-email: zhling2012@live.com
License: UNKNOWN
Platform: UNKNOWN
Classifier: Programming Language :: Python :: 3
Classifier: License :: OSI Approved :: MIT License
Classifier: Operating System :: OS Independent
Requires-Dist: matplotlib
Requires-Dist: numpy (==1.19.3)
Requires-Dist: pyautogui
Requires-Dist: requests
Requires-Dist: basecolors (==0.0.2)
Requires-Dist: pillow
Requires-Dist: scikit-image
Requires-Dist: redis
